account_generator_helper/__init__.py
account_generator_helper/countries.py
account_generator_helper/utilities.py
account_generator_helper/captcha_solver/__init__.py
account_generator_helper/captcha_solver/exceptions.py
account_generator_helper/fake_data/__init__.py
account_generator_helper/fake_data/const.py
account_generator_helper/fake_data/exceptions.py
account_generator_helper/fake_data/utilities.py
account_generator_helper/proxies/__init__.py
account_generator_helper/proxies/constants.py
account_generator_helper/proxies/proxy.py
account_generator_helper/temp_mail/__init__.py
account_generator_helper/temp_mail/exceptions.py
account_generator_helper/temp_mail/gmailnator/__init__.py
account_generator_helper/temp_mail/gmailnator/letter.py
account_generator_helper/temp_mail/inboxkitten/__init__.py
account_generator_helper/temp_mail/inboxkitten/letter.py
account_generator_helper/temp_mail/mail/__init__.py
account_generator_helper/temp_mail/mail/letter.py
account_generator_helper/temp_mail/tempmail/__init__.py
account_generator_helper/temp_mail/tempmail/letter.py
account_generator_helper/temp_mail/tempmaillol/__init__.py
account_generator_helper/temp_mail/tempmaillol/letter.py
account_generator_helper/temp_mail/tempmailplus/__init__.py
account_generator_helper/temp_mail/tempmailplus/letter.py
account_generator_helper/temp_mail/tempmailplus/tempmailplusdomains.py
account_generator_helper/temp_phone/__init__.py
account_generator_helper/temp_phone/exceptions.py
account_generator_helper/temp_phone/message.py
account_generator_helper/temp_phone/receive/__init__.py
account_generator_helper/temp_phone/receive/country.py
account_generator_helper/temp_phone/receive/phone.py
account_generator_helper/temp_phone/receive_sms/__init__.py
account_generator_helper/temp_phone/receive_sms/country.py
account_generator_helper/temp_phone/receive_sms/phone.py
account_generator_helper-1.0.14.dist-info/LICENSE
account_generator_helper-1.0.14.dist-info/METADATA
account_generator_helper-1.0.14.dist-info/WHEEL
account_generator_helper-1.0.14.dist-info/top_level.txt
account_generator_helper-1.0.14.dist-info/RECORD
