Metadata-Version: 2.1
Name: account-generator-helper
Version: 1.0.14
Summary: This library is helpful when creating accounts, it has everything you need for this
Home-page: https://github.com/DioniS1902/AccountGeneratorHelper
Author: Dionis1902
Author-email: den70007.ua@gmail.com
License: MIT
Project-URL: Source, https://github.com/Dionis1902/AccountGeneratorHelper/tree/main/account_generator_helper
Project-URL: Examples, https://github.com/Dionis1902/AccountGeneratorHelper/tree/main/examples
Project-URL: Tracker, https://github.com/Dionis1902/AccountGeneratorHelper/issues
Keywords: python email captcha proxy pypi sms gmail temp-mail captcha-solving captcha-solver fake-data account-generator captcha-recognition fake-data-generator free-proxy recive-sms gmailnator gmailnator-api poxies
Classifier: Development Status :: 3 - Alpha
Classifier: License :: OSI Approved :: MIT License
Classifier: Environment :: Console
Classifier: Intended Audience :: Developers
Classifier: Natural Language :: English
Classifier: Operating System :: OS Independent
Classifier: Programming Language :: Python :: 3
Classifier: Programming Language :: Python :: 3 :: Only
Classifier: Programming Language :: Python :: 3.6
Classifier: Programming Language :: Python :: 3.7
Classifier: Programming Language :: Python :: 3.8
Classifier: Programming Language :: Python :: 3.9
Classifier: Programming Language :: Python :: 3.10
Classifier: Topic :: Communications :: Email
Classifier: Topic :: Utilities
Classifier: Topic :: Internet :: Proxy Servers
Requires-Python: >=3
License-File: LICENSE
Requires-Dist: certifi (==2022.12.7)
Requires-Dist: charset-normalizer (==2.0.12)
Requires-Dist: idna (==3.3)
Requires-Dist: requests (==2.27.1)
Requires-Dist: urllib3 (==1.26.9)
Requires-Dist: beautifulsoup4 (~=4.10.0)
Requires-Dist: pysocks (==1.7.1)
Requires-Dist: cloudscraper (==1.2.69)
